<annotation>
	<folder>in-office</folder>
	<filename>close_0522.jpg</filename>
	<path>./in-office/close_0522.jpg</path>
	<source>
		<database>Unknown</database>
	</source>
	<size>
		<width>800</width>
		<height>800</height>
		<depth>3</depth>
	</size>
	<segmented>0</segmented>
	<object>
		<name>head</name>
		<pose>Unspecified</pose>
		<truncated>0</truncated>
		<difficult>0</difficult>
		<bndbox>
			<xmin>128</xmin>
			<ymin>189</ymin>
			<xmax>163</xmax>
			<ymax>228</ymax>
		</bndbox>
	</object>
	<object>
		<name>head</name>
		<pose>Unspecified</pose>
		<truncated>0</truncated>
		<difficult>0</difficult>
		<bndbox>
			<xmin>85</xmin>
			<ymin>396</ymin>
			<xmax>136</xmax>
			<ymax>435</ymax>
		</bndbox>
	</object>
	<object>
		<name>head</name>
		<pose>Unspecified</pose>
		<truncated>0</truncated>
		<difficult>0</difficult>
		<bndbox>
			<xmin>663</xmin>
			<ymin>209</ymin>
			<xmax>719</xmax>
			<ymax>260</ymax>
		</bndbox>
	</object>
	<object>
		<name>head</name>
		<pose>Unspecified</pose>
		<truncated>0</truncated>
		<difficult>0</difficult>
		<bndbox>
			<xmin>434</xmin>
			<ymin>87</ymin>
			<xmax>465</xmax>
			<ymax>127</ymax>
		</bndbox>
	</object>
	<object>
		<name>head</name>
		<pose>Unspecified</pose>
		<truncated>0</truncated>
		<difficult>0</difficult>
		<bndbox>
			<xmin>467</xmin>
			<ymin>114</ymin>
			<xmax>505</xmax>
			<ymax>160</ymax>
		</bndbox>
	</object>
	<object>
		<name>head</name>
		<pose>Unspecified</pose>
		<truncated>0</truncated>
		<difficult>0</difficult>
		<bndbox>
			<xmin>373</xmin>
			<ymin>217</ymin>
			<xmax>412</xmax>
			<ymax>266</ymax>
		</bndbox>
	</object>
	<object>
		<name>head</name>
		<pose>Unspecified</pose>
		<truncated>0</truncated>
		<difficult>0</difficult>
		<bndbox>
			<xmin>451</xmin>
			<ymin>268</ymin>
			<xmax>490</xmax>
			<ymax>305</ymax>
		</bndbox>
	</object>
	<object>
		<name>head</name>
		<pose>Unspecified</pose>
		<truncated>0</truncated>
		<difficult>0</difficult>
		<bndbox>
			<xmin>634</xmin>
			<ymin>401</ymin>
			<xmax>695</xmax>
			<ymax>458</ymax>
		</bndbox>
	</object>
	<object>
		<name>head</name>
		<pose>Unspecified</pose>
		<truncated>0</truncated>
		<difficult>0</difficult>
		<bndbox>
			<xmin>678</xmin>
			<ymin>291</ymin>
			<xmax>733</xmax>
			<ymax>335</ymax>
		</bndbox>
	</object>
	<object>
		<name>head</name>
		<pose>Unspecified</pose>
		<truncated>0</truncated>
		<difficult>0</difficult>
		<bndbox>
			<xmin>687</xmin>
			<ymin>83</ymin>
			<xmax>724</xmax>
			<ymax>125</ymax>
		</bndbox>
	</object>
</annotation>
