<annotation>
	<folder>in-office</folder>
	<filename>close_0627.jpg</filename>
	<path>./in-office/close_0627.jpg</path>
	<source>
		<database>Unknown</database>
	</source>
	<size>
		<width>800</width>
		<height>800</height>
		<depth>3</depth>
	</size>
	<segmented>0</segmented>
	<object>
		<name>head</name>
		<pose>Unspecified</pose>
		<truncated>0</truncated>
		<difficult>0</difficult>
		<bndbox>
			<xmin>490</xmin>
			<ymin>517</ymin>
			<xmax>550</xmax>
			<ymax>571</ymax>
		</bndbox>
	</object>
	<object>
		<name>head</name>
		<pose>Unspecified</pose>
		<truncated>0</truncated>
		<difficult>0</difficult>
		<bndbox>
			<xmin>522</xmin>
			<ymin>399</ymin>
			<xmax>574</xmax>
			<ymax>445</ymax>
		</bndbox>
	</object>
	<object>
		<name>head</name>
		<pose>Unspecified</pose>
		<truncated>0</truncated>
		<difficult>0</difficult>
		<bndbox>
			<xmin>419</xmin>
			<ymin>369</ymin>
			<xmax>471</xmax>
			<ymax>417</ymax>
		</bndbox>
	</object>
	<object>
		<name>head</name>
		<pose>Unspecified</pose>
		<truncated>0</truncated>
		<difficult>0</difficult>
		<bndbox>
			<xmin>682</xmin>
			<ymin>165</ymin>
			<xmax>722</xmax>
			<ymax>207</ymax>
		</bndbox>
	</object>
	<object>
		<name>head</name>
		<pose>Unspecified</pose>
		<truncated>0</truncated>
		<difficult>0</difficult>
		<bndbox>
			<xmin>624</xmin>
			<ymin>169</ymin>
			<xmax>660</xmax>
			<ymax>207</ymax>
		</bndbox>
	</object>
	<object>
		<name>head</name>
		<pose>Unspecified</pose>
		<truncated>0</truncated>
		<difficult>0</difficult>
		<bndbox>
			<xmin>353</xmin>
			<ymin>276</ymin>
			<xmax>397</xmax>
			<ymax>315</ymax>
		</bndbox>
	</object>
	<object>
		<name>head</name>
		<pose>Unspecified</pose>
		<truncated>0</truncated>
		<difficult>0</difficult>
		<bndbox>
			<xmin>274</xmin>
			<ymin>311</ymin>
			<xmax>314</xmax>
			<ymax>344</ymax>
		</bndbox>
	</object>
	<object>
		<name>head</name>
		<pose>Unspecified</pose>
		<truncated>0</truncated>
		<difficult>0</difficult>
		<bndbox>
			<xmin>73</xmin>
			<ymin>268</ymin>
			<xmax>110</xmax>
			<ymax>302</ymax>
		</bndbox>
	</object>
	<object>
		<name>head</name>
		<pose>Unspecified</pose>
		<truncated>0</truncated>
		<difficult>0</difficult>
		<bndbox>
			<xmin>61</xmin>
			<ymin>418</ymin>
			<xmax>104</xmax>
			<ymax>459</ymax>
		</bndbox>
	</object>
	<object>
		<name>head</name>
		<pose>Unspecified</pose>
		<truncated>0</truncated>
		<difficult>0</difficult>
		<bndbox>
			<xmin>694</xmin>
			<ymin>75</ymin>
			<xmax>729</xmax>
			<ymax>118</ymax>
		</bndbox>
	</object>
</annotation>
